TelegramPremiumFix/__init__.py
telegrampremiumfix-1.7.6.dist-info/METADATA
telegrampremiumfix-1.7.6.dist-info/WHEEL
telegrampremiumfix-1.7.6.dist-info/top_level.txt
telegrampremiumfix-1.7.6.dist-info/RECORD
