Metadata-Version: 2.4
Name: TelegramPremiumFix
Version: 1.7.6
Summary: Use this library for add Premium to your telegram
Author: MaksVavrik
Requires-Python: >=3.6
Dynamic: author
Dynamic: requires-python
Dynamic: summary
